{
    "version": "0.1.3",
    "description": "Local-first Git workflow configurator for real repositories.",
    "homepage": "https://github.com/postigodev/koba",
    "license": "MIT",
    "architecture": {
        "64bit": {
            "url": "https://github.com/postigodev/koba/releases/download/v0.1.3/koba-x86_64-pc-windows-msvc.zip",
            "hash": "057a485f63bc442909ffa9ee9f769d306d26be6d275f8f3f0862911540e7499c"
        }
    },
    "bin": "koba.exe",
    "checkver": "github",
    "autoupdate": {
        "architecture": {
            "64bit": {
                "url": "https://github.com/postigodev/koba/releases/download/v$version/koba-x86_64-pc-windows-msvc.zip"
            }
        },
        "hash": {
            "url": "$url.sha256"
        }
    }
}
